sopel_amputator/__init__.py
sopel_amputator-0.3.0.dist-info/licenses/COPYING
sopel_amputator-0.3.0.dist-info/METADATA
sopel_amputator-0.3.0.dist-info/WHEEL
sopel_amputator-0.3.0.dist-info/entry_points.txt
sopel_amputator-0.3.0.dist-info/top_level.txt
sopel_amputator-0.3.0.dist-info/RECORD
