Metadata-Version: 2.4
Name: sopel-amputator
Version: 0.3.0
Summary: Sopel plugin that detects AMP links and finds their canonical forms using AmputatorBot
Author-email: dgw <dgw@technobabbl.es>
License-Expression: EFL-2.0
Project-URL: Homepage, https://github.com/dgw/sopel-amputator
Project-URL: Bug Tracker, https://github.com/dgw/sopel-amputator/issues
Keywords: sopel,plugin,bot,irc
Platform: Linux x86, x86-64
Classifier: Intended Audience :: Developers
Classifier: Intended Audience :: System Administrators
Classifier: Topic :: Communications :: Chat :: Internet Relay Chat
Requires-Python: <4,>=3.8
License-File: COPYING
Requires-Dist: sopel>=8.0
Dynamic: license-file
